{"State.4bf346ae-8454-4c8e-afde-b74a515542e8": {"id": "2a66b473-7feb-43fd-9e78-9bd2e299da83", "created_at": "2020-08-13T15:17:55.531924", "updated_at": "2020-08-13T15:17:55.531973", "name": "California", "__class__": "State"}, "State.623288d0-05e8-45d5-82fa-343efa5945f9": {"id": "fb8aa808-a34f-42e7-8062-47de7725d084", "created_at": "2020-08-13T15:17:55.532325", "updated_at": "2020-08-13T15:17:55.532352", "name": "Arizona", "__class__": "State"}, "Place.b4e07b54-42d1-4f5f-a8b7-e680d8bae133": {"id": "5eac5724-552f-485a-bde7-957cf511c344", "created_at": "2020-08-13T15:17:55.532892", "updated_at": "2020-08-13T15:17:55.532954", "city_id": "0a01", "user_id": "0001", "name": "My little house", "number_rooms": "4", "number_bathrooms": "2", "max_guest": "10", "price_by_night": "300", "latitude": "37.773972", "longitude": "-122.431297", "__class__": "Place"}, "State.b24b0df2-a327-4615-af95-4bf1978277fe": {"id": "b24b0df2-a327-4615-af95-4bf1978277fe", "created_at": "2020-08-13T15:22:18.714104", "updated_at": "2020-08-13T15:22:18.714112", "name": "California", "__class__": "State"}, "State.9594a25d-1124-4f1e-8241-c3716f504680": {"id": "9594a25d-1124-4f1e-8241-c3716f504680", "created_at": "2020-08-13T15:22:18.714684", "updated_at": "2020-08-13T15:22:18.714688", "name": "Nevada", "__class__": "State"}}